pysapets/__init__.py
pysapets/animal.py
pysapets/ant.py
pysapets/battle.py
pysapets/constants.py
pysapets/cricket.py
pysapets/horse.py
pysapets/mosquito.py
pysapets/zombie_cricket.py
pysapets-0.0.1.dist-info/LICENSE
pysapets-0.0.1.dist-info/METADATA
pysapets-0.0.1.dist-info/WHEEL
pysapets-0.0.1.dist-info/top_level.txt
pysapets-0.0.1.dist-info/RECORD
